[
  {
    "label": "ORG",
    "url": "https://usa4-bms-02.shegu.net/vip/p1/org_tv/9/9/9/3/tv.9.S3E6.original.2744780.20231019154638.mkv?KEY1=VmeFeBCFb7ryv0i6fSGKoQ&KEY2=1748105094&KEY3=782470&KEY4=world&KEY5=Game.of.Thrones.S03E06.2160p.%5BHDR%5D.%5B5.1.7.1.5.1%5D.%5Bger.eng.eng%5D.%5BVio%5D.mkv&KEY7=febbox_video_quality_list_v3&KEY8=782470"
  },
  {
    "label": "4K",
    "url": "https://usa4-bms-02.shegu.net/vip/p1/tv_mp4_h264/9/9/9/3/tv.9.S3E6.4K.HDR.H265.20231019135624.mp4?KEY1=ww3NAHPZWWg3g_0ckRAd0Q&KEY2=1748105094&KEY3=782470&KEY4=world&KEY7=febbox_video_quality_list_v3&KEY8=782470"
  },
  {
    "label": "1080P",
    "url": "https://usa4-bms-02.shegu.net/vip/p1/tv_mp4_h264/9/9/9/3/tv.9.S3E6.1080p.HDR.H265.20231019135624.mp4?KEY1=tzv-28ADN-b3_4l-ZYdACA&KEY2=1748105094&KEY3=782470&KEY4=world&KEY7=febbox_video_quality_list_v3&KEY8=782470"
  }
]