[
  {
    "label": "ORG",
    "url": "https://uk1-as204.shegu.net/vip/p1/org_tv/9/9/9/6/tv.9.S6E10.original.1748437.20191213025157.mp4?KEY1=Nl6qaJkor85CmqK6NNXvrQ&KEY2=1748105341&KEY3=782470&KEY4=world&KEY5=game.of.thrones.s06e10.1080p.bluray.x264-rovers.mkv&KEY7=febbox_video_quality_list_v3&KEY8=782470"
  },
  {
    "label": "1080P",
    "url": "https://uk1-as205.shegu.net/vip/p1/tv_mp4_h264/9/9/9/6/tv.9.S6E10.1080p.H264.20200608065503.mp4?KEY1=ei3-EJou_GeM1Nxk3-Ftgw&KEY2=1748105341&KEY3=782470&KEY4=world&KEY7=febbox_video_quality_list_v3&KEY8=782470"
  },
  {
    "label": "720P",
    "url": "https://uk1-avs02-1.shegu.net/vip/p1/tv_mp4_h264/9/9/9/6/tv.9.S6E10.1080p.H264.20191213023311.mp4?KEY1=RM5BpD5bDpU238TYcg5ajw&KEY2=1748105341&KEY3=782470&KEY4=world&KEY7=febbox_video_quality_list_v3&KEY8=782470"
  },
  {
    "label": "360P",
    "url": "https://uk1-as205-1.shegu.net/vip/p1/tv_mp4_h264/9/9/9/6/tv.9.S6E10.360p.H264.20191213023311.mp4?KEY1=kZJU0iLHQ8lkQ_aS2k-eVg&KEY2=1748105341&KEY3=782470&KEY4=world&KEY7=febbox_video_quality_list_v3&KEY8=782470"
  }
]