[
  {
    "label": "ORG",
    "url": "https://hk1.shegu.net/vip/p1/org_tv/9/9/9/4/tv.9.S4E1.original.2744785.20231019134813.mkv?KEY1=28pLX6rFVpuSP6wnQmd-Pw&KEY2=1748105125&KEY3=782470&KEY4=world&KEY5=Game.of.Thrones.S04E01.2160p.%5BHDR%5D.%5B5.1.7.1.5.1%5D.%5Bger.eng.eng%5D.%5BVio%5D.mkv&KEY7=febbox_video_quality_list_v3&KEY8=782470"
  },
  {
    "label": "4K",
    "url": "https://hk1.shegu.net/vip/p1/tv_mp4_h264/9/9/9/4/tv.9.S4E1.4K.HDR.H265.20231019121242.mp4?KEY1=cAJWCYBStbXn-CUq9ZT-1Q&KEY2=1748105124&KEY3=782470&KEY4=world&KEY7=febbox_video_quality_list_v3&KEY8=782470"
  },
  {
    "label": "1080P",
    "url": "https://hk1.shegu.net/vip/p1/tv_mp4_h264/9/9/9/4/tv.9.S4E1.1080p.HDR.H265.20231019121242.mp4?KEY1=GX-Ur4sLkG40jywJQO8F1g&KEY2=1748105124&KEY3=782470&KEY4=world&KEY7=febbox_video_quality_list_v3&KEY8=782470"
  }
]