[
  {
    "fid": "2672614",
    "name": "The.X-Files.S05E20.Multi.1080p.BluRay.DTS-HDMA.H.264-IMPERIUM.mkv",
    "episodeNum": 20
  },
  {
    "fid": "2672613",
    "name": "The.X-Files.S05E19.Multi.1080p.BluRay.DTS-HDMA.H.264-IMPERIUM.mkv",
    "episodeNum": 19
  },
  {
    "fid": "2672612",
    "name": "The.X-Files.S05E18.Multi.1080p.BluRay.DTS-HDMA.H.264-IMPERIUM.mkv",
    "episodeNum": 18
  },
  {
    "fid": "2672611",
    "name": "The.X-Files.S05E17.Multi.1080p.BluRay.DTS-HDMA.H.264-IMPERIUM.mkv",
    "episodeNum": 17
  },
  {
    "fid": "2672610",
    "name": "The.X-Files.S05E16.Multi.1080p.BluRay.DTS-HDMA.H.264-IMPERIUM.mkv",
    "episodeNum": 16
  },
  {
    "fid": "2672609",
    "name": "The.X-Files.S05E15.Multi.1080p.BluRay.DTS-HDMA.H.264-IMPERIUM.mkv",
    "episodeNum": 15
  },
  {
    "fid": "2672608",
    "name": "The.X-Files.S05E14.Multi.1080p.BluRay.DTS-HDMA.H.264-IMPERIUM.mkv",
    "episodeNum": 14
  },
  {
    "fid": "2672607",
    "name": "The.X-Files.S05E13.Multi.1080p.BluRay.DTS-HDMA.H.264-IMPERIUM.mkv",
    "episodeNum": 13
  },
  {
    "fid": "2672606",
    "name": "The.X-Files.S05E12.Multi.1080p.BluRay.DTS-HDMA.H.264-IMPERIUM.mkv",
    "episodeNum": 12
  },
  {
    "fid": "2672605",
    "name": "The.X-Files.S05E11.Multi.1080p.BluRay.DTS-HDMA.H.264-IMPERIUM.mkv",
    "episodeNum": 11
  },
  {
    "fid": "2672604",
    "name": "The.X-Files.S05E10.Multi.1080p.BluRay.DTS-HDMA.H.264-IMPERIUM.mkv",
    "episodeNum": 10
  },
  {
    "fid": "2672603",
    "name": "The.X-Files.S05E09.Multi.1080p.BluRay.DTS-HDMA.H.264-IMPERIUM.mkv",
    "episodeNum": 9
  },
  {
    "fid": "2672602",
    "name": "The.X-Files.S05E08.Multi.1080p.BluRay.DTS-HDMA.H.264-IMPERIUM.mkv",
    "episodeNum": 8
  },
  {
    "fid": "2672601",
    "name": "The.X-Files.S05E07.Multi.1080p.BluRay.DTS-HDMA.H.264-IMPERIUM.mkv",
    "episodeNum": 7
  },
  {
    "fid": "2672600",
    "name": "The.X-Files.S05E06.Multi.1080p.BluRay.DTS-HDMA.H.264-IMPERIUM.mkv",
    "episodeNum": 6
  },
  {
    "fid": "2672599",
    "name": "The.X-Files.S05E05.Multi.1080p.BluRay.DTS-HDMA.H.264-IMPERIUM.mkv",
    "episodeNum": 5
  },
  {
    "fid": "2672598",
    "name": "The.X-Files.S05E04.Multi.1080p.BluRay.DTS-HDMA.H.264-IMPERIUM.mkv",
    "episodeNum": 4
  },
  {
    "fid": "2672595",
    "name": "The.X-Files.S05E01.Multi.1080p.BluRay.DTS-HDMA.H.264-IMPERIUM.mkv",
    "episodeNum": 1
  },
  {
    "fid": "2672597",
    "name": "The.X-Files.S05E03.Multi.1080p.BluRay.DTS-HDMA.H.264-IMPERIUM.mkv",
    "episodeNum": 3
  },
  {
    "fid": "2672596",
    "name": "The.X-Files.S05E02.Multi.1080p.BluRay.DTS-HDMA.H.264-IMPERIUM.mkv",
    "episodeNum": 2
  }
]