[
  {
    "fid": "2637840",
    "name": "The.Blacklist.S08E22.1080p.WEB.H264-STRONTiUM.mkv",
    "episodeNum": 22
  },
  {
    "fid": "2637839",
    "name": "The.Blacklist.S08E21.1080p.WEB.H264-STRONTiUM.mkv",
    "episodeNum": 21
  },
  {
    "fid": "2637838",
    "name": "The.Blacklist.S08E20.1080p.WEB.H264-STRONTiUM.mkv",
    "episodeNum": 20
  },
  {
    "fid": "2637837",
    "name": "The.Blacklist.S08E19.Balthazar.Bino.Baker.1080p.AMZN.WEB-DL.DDP5.1.H.264-NTb.mkv",
    "episodeNum": 19
  },
  {
    "fid": "2637836",
    "name": "The.Blacklist.S08E18.1080p.WEB.H264-STRONTiUM.mkv",
    "episodeNum": 18
  },
  {
    "fid": "2637835",
    "name": "The.Blacklist.S08E17.Ivan.Stepanov.1080p.AMZN.WEB-DL.DDP5.1.H.264-NTb.mkv",
    "episodeNum": 17
  },
  {
    "fid": "2637834",
    "name": "the.blacklist.s08e16.720p.hdtv.x264-syncopy.mkv",
    "episodeNum": 16
  },
  {
    "fid": "2637833",
    "name": "The.Blacklist.S08E15.iNTERNAL.1080p.WEB.H264-STRONTiUM.mkv",
    "episodeNum": 15
  },
  {
    "fid": "2637832",
    "name": "The.Blacklist.S08E14.Misere.1080p.AMZN.WEB-DL.DDP5.1.H.264-NTb.mkv",
    "episodeNum": 14
  },
  {
    "fid": "2637831",
    "name": "The.Blacklist.S08E13.Anne.1080p.AMZN.WEB-DL.DDP5.1.H.264-NTb.mkv",
    "episodeNum": 13
  },
  {
    "fid": "2637829",
    "name": "The.Blacklist.S08E11.1080p.WEB.H264-STRONTiUM.2514898.mkv",
    "episodeNum": 11
  },
  {
    "fid": "2637830",
    "name": "The.Blacklist.S08E12.1080p.WEB.H264-STRONTiUM.mkv",
    "episodeNum": 12
  },
  {
    "fid": "2637828",
    "name": "The.Blacklist.S08E10.1080p.WEB.H264-STRONTiUM.mkv",
    "episodeNum": 10
  },
  {
    "fid": "2637827",
    "name": "The.Blacklist.S08E09.PROPER.1080p.WEB.H264-STRONTiUM.mkv",
    "episodeNum": 9
  },
  {
    "fid": "2637826",
    "name": "The.Blacklist.S08E08.Ogden.Greely.1080p.AMZN.WEB-DL.DDP5.1.H.264-NTb.mkv",
    "episodeNum": 8
  },
  {
    "fid": "2637825",
    "name": "afi-the.blacklist.s08e07.1080p.mkv",
    "episodeNum": 7
  },
  {
    "fid": "2637824",
    "name": "The.Blacklist.S08E07.Chemical.Mary.1080p.AMZN.WEB-DL.DDP5.1.H.264-NTb.mkv",
    "episodeNum": 7
  },
  {
    "fid": "2637823",
    "name": "afi-the.blacklist.s08e06.1080p.mkv",
    "episodeNum": 6
  },
  {
    "fid": "2637822",
    "name": "the.blacklist.s08e05.1080p.web.h264-cakes.mkv",
    "episodeNum": 5
  },
  {
    "fid": "2637821",
    "name": "The.Blacklist.S08E04.Elizabeth.Keen.1080p.AMZN.WEB-DL.DDP5.1.H.264-NTb.mkv",
    "episodeNum": 4
  },
  {
    "fid": "2637820",
    "name": "The.Blacklist.S08E03.1080p.WEB.h264-WEBTUBE.mkv",
    "episodeNum": 3
  },
  {
    "fid": "2637818",
    "name": "The.Blacklist.S08E01.Roanoke.1080p.AMZN.WEB-DL.DDP5.1.H.264-NTb.mkv",
    "episodeNum": 1
  },
  {
    "fid": "2637819",
    "name": "The.Blacklist.S08E02.1080p.WEB.H264-STRONTiUM.mkv",
    "episodeNum": 2
  }
]