[
  {
    "fid": "2714666",
    "name": "top.chef.s17e13.1080p.web.h264-oath.mkv",
    "episodeNum": 13
  },
  {
    "fid": "2714667",
    "name": "top.chef.s17e14.1080p.web.h264-oath.mkv",
    "episodeNum": 14
  },
  {
    "fid": "2714664",
    "name": "top.chef.s17e11.1080p.web.h264-oath.mkv",
    "episodeNum": 11
  },
  {
    "fid": "2714665",
    "name": "top.chef.s17e12.1080p.web.h264-oath.mkv",
    "episodeNum": 12
  },
  {
    "fid": "2714661",
    "name": "top.chef.s17e08.1080p.web.x264-xlf.mkv",
    "episodeNum": 8
  },
  {
    "fid": "2714662",
    "name": "Top.Chef.S17E09.1080p.WEB.x264-ROBOTS.mkv",
    "episodeNum": 9
  },
  {
    "fid": "2714663",
    "name": "Top.Chef.S17E10.Colossal.Coliseum.Kaiseki.1080p.AMZN.WEB-DL.DDP5.1.H.264-NTb.mkv",
    "episodeNum": 10
  },
  {
    "fid": "2714659",
    "name": "Top.Chef.S17E06.1080p.HDTV.x264-CRiMSON.mkv",
    "episodeNum": 6
  },
  {
    "fid": "2714660",
    "name": "Top.Chef.S17E07.1080p.HDTV.x264-CRiMSON.mkv",
    "episodeNum": 7
  },
  {
    "fid": "2714656",
    "name": "Top.Chef.S17E03.Strokes.of.Genius.1080p.HDTV.x264-CRiMSON.mkv",
    "episodeNum": 3
  },
  {
    "fid": "2714657",
    "name": "Top.Chef.S17E04.1080p.HDTV.x264-CRiMSON.mkv",
    "episodeNum": 4
  },
  {
    "fid": "2714658",
    "name": "top.chef.s17e05.1080p.web.x264-flx.mkv",
    "episodeNum": 5
  },
  {
    "fid": "2714654",
    "name": "Top.Chef.S17E01.1080p.HDTV.x264-CRiMSON.mkv",
    "episodeNum": 1
  },
  {
    "fid": "2714655",
    "name": "Top.Chef.S17E02.1080p.HDTV.x264-CRiMSON.mkv",
    "episodeNum": 2
  }
]