[
  {
    "fid": "2619581",
    "name": "greys.anatomy.1123.hdtv-lol.mp4",
    "episodeNum": 123
  },
  {
    "fid": "2619583",
    "name": "Grey.s.Anatomy.S11E25.Youre.My.Home.1080p.AMZN.WEB-DL.DDP5.1.H.264-NTb.mkv",
    "episodeNum": 25
  },
  {
    "fid": "2619582",
    "name": "Grey.s.Anatomy.S11E24.Time.Stops.1080p.AMZN.WEB-DL.AAC2.0.x264-NTb.mkv",
    "episodeNum": 24
  },
  {
    "fid": "2619580",
    "name": "Grey.s.Anatomy.S11E22.Shes.Leaving.Home.1080p.AMZN.WEB-DL.AAC2.0.x264-NTb.mkv",
    "episodeNum": 22
  },
  {
    "fid": "2619579",
    "name": "Grey.s.Anatomy.S11E21.How.to.Save.a.Life.1080p.AMZN.WEB-DL.AAC2.0.x264-NTb.mkv",
    "episodeNum": 21
  },
  {
    "fid": "2619578",
    "name": "Grey.s.Anatomy.S11E20.One.Flight.Down.1080p.AMZN.WEB-DL.DDP5.1.x264-NTb.mkv",
    "episodeNum": 20
  },
  {
    "fid": "2619577",
    "name": "Grey.s.Anatomy.S11E19.Crazy.Love.1080p.AMZN.WEB-DL.DDP5.1.x264-NTb.mkv",
    "episodeNum": 19
  },
  {
    "fid": "2619576",
    "name": "Grey.s.Anatomy.S11E18.When.I.Grow.Up.1080p.AMZN.WEB-DL.DDP5.1.x264-NTb.mkv",
    "episodeNum": 18
  },
  {
    "fid": "2619575",
    "name": "Grey.s.Anatomy.S11E17.With.or.Without.You.1080p.AMZN.WEB-DL.AAC2.0.x264-NTb.mkv",
    "episodeNum": 17
  },
  {
    "fid": "2619574",
    "name": "Grey.s.Anatomy.S11E16.Dont.Dream.Its.Over.1080p.AMZN.WEB-DL.DDP5.1.x264-NTb.mkv",
    "episodeNum": 16
  },
  {
    "fid": "2619573",
    "name": "Grey.s.Anatomy.S11E15.I.Feel.the.Earth.Move.1080p.AMZN.WEB-DL.AAC2.0.x264-NTb.mkv",
    "episodeNum": 15
  },
  {
    "fid": "2619571",
    "name": "Grey.s.Anatomy.S11E13.Staring.at.the.End.1080p.AMZN.WEB-DL.DDP5.1.x264-NTb.mkv",
    "episodeNum": 13
  },
  {
    "fid": "2619572",
    "name": "Grey.s.Anatomy.S11E14.The.Distance.1080p.AMZN.WEB-DL.DDP5.1.x264-NTb.mkv",
    "episodeNum": 14
  },
  {
    "fid": "2619570",
    "name": "Grey.s.Anatomy.S11E12.The.Great.Pretender.1080p.AMZN.WEB-DL.DDP5.1.x264-NTb.mkv",
    "episodeNum": 12
  },
  {
    "fid": "2619569",
    "name": "Grey.s.Anatomy.S11E11.All.I.Could.Do.Was.Cry.1080p.AMZN.WEB-DL.DDP5.1.x264-NTb.mkv",
    "episodeNum": 11
  },
  {
    "fid": "2619568",
    "name": "Grey.s.Anatomy.S11E10.The.Beds.Too.Big.Without.You.1080p.AMZN.WEB-DL.DDP5.1.x264-NTb.mkv",
    "episodeNum": 10
  },
  {
    "fid": "2619567",
    "name": "Grey.s.Anatomy.S11E09.Where.Do.We.Go.From.Here.1080p.AMZN.WEB-DL.DDP5.1.x264-NTb.mkv",
    "episodeNum": 9
  },
  {
    "fid": "2619566",
    "name": "Grey.s.Anatomy.S11E08.Risk.1080p.AMZN.WEB-DL.AAC2.0.x264-NTb.mkv",
    "episodeNum": 8
  },
  {
    "fid": "2619565",
    "name": "Grey.s.Anatomy.S11E07.Could.We.Start.Again.Please.1080p.AMZN.WEB-DL.DDP5.1.x264-NTb.mkv",
    "episodeNum": 7
  },
  {
    "fid": "2619564",
    "name": "Grey.s.Anatomy.S11E06.Dont.Lets.Start.1080p.AMZN.WEB-DL.AAC2.0.x264-NTb.mkv",
    "episodeNum": 6
  },
  {
    "fid": "2619563",
    "name": "Grey.s.Anatomy.S11E05.Bend.and.Break.1080p.AMZN.WEB-DL.DDP5.1.H.264-NTb.mkv",
    "episodeNum": 5
  },
  {
    "fid": "2619562",
    "name": "Grey.s.Anatomy.S11E04.Only.Mama.Knows.1080p.AMZN.WEB-DL.DDP5.1.H.264-NTb.mkv",
    "episodeNum": 4
  },
  {
    "fid": "2619561",
    "name": "Grey.s.Anatomy.S11E03.Got.to.Be.Real.1080p.AMZN.WEB-DL.AAC2.0.x264-NTb.mkv",
    "episodeNum": 3
  },
  {
    "fid": "2619560",
    "name": "Grey.s.Anatomy.S11E02.Puzzle.With.a.Piece.Missing.1080p.AMZN.WEB-DL.AAC2.0.x264-NTb.mkv",
    "episodeNum": 2
  },
  {
    "fid": "2619559",
    "name": "Grey.s.Anatomy.S11E01.I.Must.Have.Lost.It.on.the.Wind.1080p.AMZN.WEB-DL.DDP5.1.H.264-NTb.mkv",
    "episodeNum": 1
  }
]