[
  {
    "fid": "16517853",
    "name": "the.agency.2024.s01e10.1080p.web.h264-successfulcrab[EZTVx.to].mkv",
    "episodeNum": 10
  },
  {
    "fid": "16078414",
    "name": "the.agency.2024.s01e09.1080p.web.h264-successfulcrab[EZTVx.to].mkv",
    "episodeNum": 9
  },
  {
    "fid": "15973727",
    "name": "The.Agency.2024.S01E08.1080p.WEB.h264-ETHEL[EZTVx.to].mkv",
    "episodeNum": 8
  },
  {
    "fid": "15882794",
    "name": "The.Agency.2024.S01E08.1080p.HEVC.x265-MeGusta[EZTVx.to].mkv",
    "episodeNum": 8
  },
  {
    "fid": "15652218",
    "name": "The.Agency.2024.S01E07.1080p.HEVC.x265-MeGusta[EZTVx.to].mkv",
    "episodeNum": 7
  },
  {
    "fid": "15523284",
    "name": "The Agency 2024 S01E05 Rat Trap 2160p PMTP WEB-DL DDP5 1 DV H 265-NTb.mkv",
    "episodeNum": 5
  },
  {
    "fid": "15522025",
    "name": "The Agency 2024 S01E06 Spy For Sale 2160p PMTP WEB-DL DDP5 1 DV HDR H 265-FLUX.mkv",
    "episodeNum": 6
  },
  {
    "fid": "15522024",
    "name": "The Agency 2024 S01E04 Quarterback Blitz 2160p PMTP WEB-DL DDP5 1 DV H 265-FLUX.mkv",
    "episodeNum": 4
  },
  {
    "fid": "15522023",
    "name": "The Agency 2024 S01E03 Hawk from a Handsaw 2160p PMTP WEB-DL DDP5 1 DV H 265-NTb.mkv",
    "episodeNum": 3
  },
  {
    "fid": "15459487",
    "name": "The.Agency.2024.S01E06.1080p.HEVC.x265-MeGusta[EZTVx.to].mkv",
    "episodeNum": 6
  },
  {
    "fid": "15272816",
    "name": "the.agency.2024.s01e05.1080p.web.h264-successfulcrab[EZTVx.to].mkv",
    "episodeNum": 5
  },
  {
    "fid": "15078401",
    "name": "The.Agency.2024.S01E04.1080p.x265-ELiTE.mkv",
    "episodeNum": 4
  },
  {
    "fid": "14880116",
    "name": "The Agency 2024 S01E03 Hawk from a Handsaw 1080p AMZN WEB-DL DDP5 1 H 264-FLUX.mkv",
    "episodeNum": 3
  },
  {
    "fid": "14744351",
    "name": "The Agency 2024 S01E02 Wooden Duck 2160p PMTP WEB-DL DDP5 1 DV HDR H 265-FLUX.mkv",
    "episodeNum": 2
  },
  {
    "fid": "14744349",
    "name": "The Agency 2024 S01E01 The Bends 2160p PMTP WEB-DL DDP5 1 DV HDR H 265-FLUX.mkv",
    "episodeNum": 1
  },
  {
    "fid": "14700745",
    "name": "The.Agency.2024.S01E02.1080p.AV1.10bit-MeGusta[EZTVx.to].mkv",
    "episodeNum": 2
  },
  {
    "fid": "14700743",
    "name": "The.Agency.2024.S01E01.1080p.HEVC.x265-MeGusta[EZTVx.to].mkv",
    "episodeNum": 1
  }
]