[
  {
    "fid": "2666843",
    "name": "better.call.saul.s05e09.1080p.web.h264-xlf.mkv",
    "episodeNum": 9
  },
  {
    "fid": "2666844",
    "name": "Better.Call.Saul.S05E10.1080p.WEB.X264-METCON.mkv",
    "episodeNum": 10
  },
  {
    "fid": "2666840",
    "name": "better.call.saul.s05e06.1080p.web.h264-xlf.mkv",
    "episodeNum": 6
  },
  {
    "fid": "2666841",
    "name": "better.call.saul.s05e07.1080p.web.h264-xlf.mkv",
    "episodeNum": 7
  },
  {
    "fid": "2666842",
    "name": "better.call.saul.s05e08.1080p.web.h264-xlf.mkv",
    "episodeNum": 8
  },
  {
    "fid": "2666837",
    "name": "better.call.saul.s05e03.1080p.web.h264-xlf.mkv",
    "episodeNum": 3
  },
  {
    "fid": "2666838",
    "name": "better.call.saul.s05e04.1080p.web.h264-xlf.mkv",
    "episodeNum": 4
  },
  {
    "fid": "2666839",
    "name": "better.call.saul.s05e05.1080p.web.h264-xlf.mkv",
    "episodeNum": 5
  },
  {
    "fid": "2666835",
    "name": "better.call.saul.s05e01.repack.1080p.web.h264-xlf.mkv",
    "episodeNum": 1
  },
  {
    "fid": "2666836",
    "name": "better.call.saul.s05e02.1080p.web.h264-xlf.mkv",
    "episodeNum": 2
  }
]