[
  {
    "fid": "2635202",
    "name": "young.sheldon.s03e21.1080p.web.x264-poke.mkv",
    "episodeNum": 21
  },
  {
    "fid": "2635201",
    "name": "young.sheldon.s03e20.1080p.web.h264-xlf.mkv",
    "episodeNum": 20
  },
  {
    "fid": "2635200",
    "name": "young.sheldon.s03e19.1080p.web.x264-poke.mkv",
    "episodeNum": 19
  },
  {
    "fid": "2635199",
    "name": "Young.Sheldon.S03E18.1080p.WEB.H264-AMCON.mkv",
    "episodeNum": 18
  },
  {
    "fid": "2635198",
    "name": "young.sheldon.s03e17.1080p.hdtv.x264-lucidtv.mkv",
    "episodeNum": 17
  },
  {
    "fid": "2635197",
    "name": "Young.Sheldon.S03E16.1080p.WEB.H264-AMCON.mkv",
    "episodeNum": 16
  },
  {
    "fid": "2635196",
    "name": "young.sheldon.s03e15.1080p.web.x264-xlf.mkv",
    "episodeNum": 15
  },
  {
    "fid": "2635195",
    "name": "young.sheldon.s03e14.1080p.web.h264-memento.mkv",
    "episodeNum": 14
  },
  {
    "fid": "2635194",
    "name": "young.sheldon.s03e13.internal.1080p.web.x264-bamboozle.mkv",
    "episodeNum": 13
  },
  {
    "fid": "2635192",
    "name": "young.sheldon.s03e11.1080p.hdtv.x264-lucidtv.mkv",
    "episodeNum": 11
  },
  {
    "fid": "2635193",
    "name": "young.sheldon.s03e12.1080p.hdtv.x264-lucidtv.mkv",
    "episodeNum": 12
  },
  {
    "fid": "2635191",
    "name": "young.sheldon.s03e10.1080p.hdtv.x264-lucidtv.mkv",
    "episodeNum": 10
  },
  {
    "fid": "2635190",
    "name": "Young.Sheldon.S03E09.1080p.WEB.H264-AMCON.mkv",
    "episodeNum": 9
  },
  {
    "fid": "2635189",
    "name": "Young.Sheldon.S03E08.1080p.HDTV.x264-LucidTV.mkv",
    "episodeNum": 8
  },
  {
    "fid": "2635188",
    "name": "Young.Sheldon.S03E07.iNTERNAL.1080p.WEB.H264-AMRAP.mkv",
    "episodeNum": 7
  },
  {
    "fid": "2635187",
    "name": "Young.Sheldon.S03E06.A.Parasol.and.a.Hell.of.an.Arm.1080p.AMZN.WEB-DL.DDP5.1.H.264-NTb.mkv",
    "episodeNum": 6
  },
  {
    "fid": "2635186",
    "name": "Young.Sheldon.S03E05.1080p.WEB.H264-AMCON.mkv",
    "episodeNum": 5
  },
  {
    "fid": "2635185",
    "name": "Young.Sheldon.S03E04.1080p.WEB.H264-AMCON.mkv",
    "episodeNum": 4
  },
  {
    "fid": "2635184",
    "name": "Young.Sheldon.S03E03.1080p.WEB.H264-AMCON.mkv",
    "episodeNum": 3
  },
  {
    "fid": "2635183",
    "name": "Young.Sheldon.S03E02.1080p.HEVC.x265-MeGusta.mkv",
    "episodeNum": 2
  },
  {
    "fid": "2635182",
    "name": "young.sheldon.s03e01.internal.1080p.web.x264-bamboozle.mkv",
    "episodeNum": 1
  }
]