[
  {
    "fid": "2721237",
    "name": "Law.Order.S03E22.Benevolence.360p.avi",
    "episodeNum": 22
  },
  {
    "fid": "2721236",
    "name": "Law.Order.S03E21.Manhood.360p.avi",
    "episodeNum": 21
  },
  {
    "fid": "2721235",
    "name": "Law.Order.S03E20.Securitate.360p.avi",
    "episodeNum": 20
  },
  {
    "fid": "2721234",
    "name": "Law.Order.S03E19.Virus.360p.avi",
    "episodeNum": 19
  },
  {
    "fid": "2721233",
    "name": "Law.Order.S03E18.360p.avi",
    "episodeNum": 18
  },
  {
    "fid": "2721231",
    "name": "Law.Order.S03E17.Conduct.Unbecoming.360p.avi",
    "episodeNum": 17
  },
  {
    "fid": "2721230",
    "name": "Law.Order.S03E16.Jurisdiction.360p.avi",
    "episodeNum": 16
  },
  {
    "fid": "2721229",
    "name": "Law.Order.S03E15.Mother.Love.360p.avi",
    "episodeNum": 15
  },
  {
    "fid": "2721228",
    "name": "Law.Order.S03E14.Promises.To.Keep.360p.avi",
    "episodeNum": 14
  },
  {
    "fid": "2721226",
    "name": "Law.Order.S03E12.Right.To.Counsel.360p.avi",
    "episodeNum": 12
  },
  {
    "fid": "2721227",
    "name": "Law.Order.S03E13.Night.And.Fog.360p.avi",
    "episodeNum": 13
  },
  {
    "fid": "2721225",
    "name": "Law.Order.S03E11Extended.Family.360p.avi",
    "episodeNum": 11
  },
  {
    "fid": "2721224",
    "name": "Law.Order.S03E10.Consultation.360p.avi",
    "episodeNum": 10
  },
  {
    "fid": "2721223",
    "name": "Law.Order.S03E09.Point.Of.View.360p.avi",
    "episodeNum": 9
  },
  {
    "fid": "2721222",
    "name": "Law.Order.S03E08.Prince.Of.Darkness.360p.avi",
    "episodeNum": 8
  },
  {
    "fid": "2721221",
    "name": "Law.Order.S03E07.Self.Defense.360p.avi",
    "episodeNum": 7
  },
  {
    "fid": "2721220",
    "name": "Law.Order.S03E06.Helpless.360p.avi",
    "episodeNum": 6
  },
  {
    "fid": "2721219",
    "name": "Law.Order.S03E05.Wedded.Bliss.360p.avi",
    "episodeNum": 5
  },
  {
    "fid": "2721218",
    "name": "Law.Order.S03E04.The.Corporate.Veil.360p.avi",
    "episodeNum": 4
  },
  {
    "fid": "2721215",
    "name": "Law.Order.S03E01.Skin.Deep.360p.avi",
    "episodeNum": 1
  },
  {
    "fid": "2721217",
    "name": "Law.Order.S03E03.Forgiveness.360p.avi",
    "episodeNum": 3
  },
  {
    "fid": "2721216",
    "name": "Law.Order.S03E02.Conspiracy.360p.avi",
    "episodeNum": 2
  }
]