{
  "adult": false,
  "backdrop_path": "/jLeMKUHRYcrrEuvolfzfIxc1mOL.jpg",
  "belongs_to_collection": null,
  "budget": 0,
  "genres": [
    {
      "id": 18,
      "name": "Drama"
    }
  ],
  "homepage": "",
  "id": 1140233,
  "imdb_id": null,
  "origin_country": [
    "KR"
  ],
  "original_language": "ko",
  "original_title": "마누라 바꿔먹기",
  "overview": "A man has an accident at work, and his boss asks his wife to have sex with him in order to free him from responsibility. One day, the man witnesses a scene where his wife has sex with his boss and decides to take revenge by doing the same to his boss' wife.",
  "popularity": 12.1639,
  "poster_path": "/lmfpb4QHehVAaLm6IEbgM0VhQuD.jpg",
  "production_companies": [],
  "production_countries": [
    {
      "iso_3166_1": "KR",
      "name": "South Korea"
    }
  ],
  "release_date": "2022-08-14",
  "revenue": 0,
  "runtime": 0,
  "spoken_languages": [
    {
      "english_name": "Korean",
      "iso_639_1": "ko",
      "name": "한국어/조선말"
    }
  ],
  "status": "Released",
  "tagline": "",
  "title": "Wife Swap",
  "video": false,
  "vote_average": 1,
  "vote_count": 1
}