{
  "adult": false,
  "backdrop_path": "/kYqEsUtilXXcb7FDfGIUaDq7j5F.jpg",
  "belongs_to_collection": null,
  "budget": 0,
  "genres": [
    {
      "id": 53,
      "name": "Thriller"
    },
    {
      "id": 35,
      "name": "Comedy"
    }
  ],
  "homepage": "",
  "id": 1101401,
  "imdb_id": "tt27165670",
  "origin_country": [
    "US"
  ],
  "original_language": "en",
  "original_title": "Sugar Baby",
  "overview": "An enterprising Sugar Baby is offered $30,000 to move in with her Sugar Daddy for the week, but soon discovers the sinister secrets trapped within his home.",
  "popularity": 22.8249,
  "poster_path": "/z7NyxmdJ1ypn3Y6BVizjGODuBdO.jpg",
  "production_companies": [
    {
      "id": 163116,
      "logo_path": "/p1JBJbwv6CvaCT0vqsJCJhhJId0.png",
      "name": "Mary Ellen Moffat",
      "origin_country": "US"
    },
    {
      "id": 121205,
      "logo_path": "/f1oMMN9etU1sT6owkPDtxFH2yMA.png",
      "name": "VMI WorldWide",
      "origin_country": "US"
    },
    {
      "id": 240793,
      "logo_path": null,
      "name": "Brook Productions",
      "origin_country": ""
    }
  ],
  "production_countries": [
    {
      "iso_3166_1": "US",
      "name": "United States of America"
    }
  ],
  "release_date": "2024-10-15",
  "revenue": 0,
  "runtime": 88,
  "spoken_languages": [
    {
      "english_name": "English",
      "iso_639_1": "en",
      "name": "English"
    }
  ],
  "status": "Released",
  "tagline": "Pay to play.",
  "title": "Sugar Baby",
  "video": false,
  "vote_average": 6.038,
  "vote_count": 13
}