{
  "adult": false,
  "backdrop_path": "/v6MPbA9ev0yttbILLjGOo2nh31h.jpg",
  "belongs_to_collection": null,
  "budget": 200000,
  "genres": [
    {
      "id": 28,
      "name": "Action"
    },
    {
      "id": 53,
      "name": "Thriller"
    }
  ],
  "homepage": "",
  "id": 1480799,
  "imdb_id": null,
  "origin_country": [
    "BR"
  ],
  "original_language": "pt",
  "original_title": "The Great Escape",
  "overview": "",
  "popularity": 214.6421,
  "poster_path": "/h7shL668vhC2wsZQSBWzxkMuZ8K.jpg",
  "production_companies": [],
  "production_countries": [],
  "release_date": "2023-05-26",
  "revenue": 0,
  "runtime": 90,
  "spoken_languages": [],
  "status": "Released",
  "tagline": "",
  "title": "The Great Escape",
  "video": false,
  "vote_average": 6.2,
  "vote_count": 2
}