{
  "adult": false,
  "backdrop_path": "/iEFuHjqrE059SmflBva1JzDJutE.jpg",
  "belongs_to_collection": {
    "id": 1241422,
    "name": "Miraculous Collection",
    "poster_path": "/tkcFT5Rwn0gpZhnIvrsVWwVZShK.jpg",
    "backdrop_path": "/9wJOhep2U74V4hUuMa64eKCXawX.jpg"
  },
  "budget": 86000000,
  "genres": [
    {
      "id": 16,
      "name": "Animation"
    },
    {
      "id": 14,
      "name": "Fantasy"
    },
    {
      "id": 28,
      "name": "Action"
    },
    {
      "id": 10749,
      "name": "Romance"
    },
    {
      "id": 10751,
      "name": "Family"
    }
  ],
  "homepage": "https://www.netflix.com/title/81383247",
  "id": 496450,
  "imdb_id": "tt10364034",
  "origin_country": [
    "FR"
  ],
  "original_language": "fr",
  "original_title": "Miraculous - le film",
  "overview": "After a guardian of magical jewels turns an awkward girl and a popular boy into superheroes, they can never reveal their identities — even to each other.",
  "popularity": 13.3572,
  "poster_path": "/dQNJ8SdCMn3zWwHzzQD2xrphR1X.jpg",
  "production_companies": [
    {
      "id": 140008,
      "logo_path": null,
      "name": "The Awakening Production",
      "origin_country": "FR"
    },
    {
      "id": 2902,
      "logo_path": "/vFmmYSgFp8eE6C34JVCXy9bJFmc.png",
      "name": "SND",
      "origin_country": "FR"
    },
    {
      "id": 200503,
      "logo_path": "/lCHoMUzKtkc8PYeFKF843lFvjWK.png",
      "name": "Fantawild",
      "origin_country": "CN"
    },
    {
      "id": 82973,
      "logo_path": null,
      "name": "Zag Animation Studios",
      "origin_country": "FR"
    },
    {
      "id": 84713,
      "logo_path": "/jrdDt2pV5OF6f4JLOhaGUMT3QO9.png",
      "name": "ON Animation Studios",
      "origin_country": "CA"
    }
  ],
  "production_countries": [
    {
      "iso_3166_1": "CN",
      "name": "China"
    },
    {
      "iso_3166_1": "FR",
      "name": "France"
    },
    {
      "iso_3166_1": "CA",
      "name": "Canada"
    }
  ],
  "release_date": "2023-07-05",
  "revenue": 40208268,
  "runtime": 107,
  "spoken_languages": [
    {
      "english_name": "English",
      "iso_639_1": "en",
      "name": "English"
    },
    {
      "english_name": "French",
      "iso_639_1": "fr",
      "name": "Français"
    }
  ],
  "status": "Released",
  "tagline": "The fate of the world is in their hands.",
  "title": "Miraculous: Ladybug & Cat Noir, The Movie",
  "video": false,
  "vote_average": 7.631,
  "vote_count": 901
}