{
  "adult": false,
  "backdrop_path": "/zt3cmdZr3t0K64gzpwIc4LXiuDu.jpg",
  "belongs_to_collection": null,
  "budget": 60000000,
  "genres": [
    {
      "id": 35,
      "name": "Comedy"
    },
    {
      "id": 18,
      "name": "Drama"
    }
  ],
  "homepage": "https://www.paramountmovies.com/movies/the-terminal",
  "id": 594,
  "imdb_id": "tt0362227",
  "origin_country": [
    "US"
  ],
  "original_language": "en",
  "original_title": "The Terminal",
  "overview": "An Eastern European tourist unexpectedly finds himself stranded in JFK airport, and must take up temporary residence there.",
  "popularity": 8.7566,
  "poster_path": "/cPB3ZMM4UdsSAhNdS4c7ps5nypY.jpg",
  "production_companies": [
    {
      "id": 7,
      "logo_path": "/vru2SssLX3FPhnKZGtYw00pVIS9.png",
      "name": "DreamWorks Pictures",
      "origin_country": "US"
    },
    {
      "id": 56,
      "logo_path": "/cEaxANEisCqeEoRvODv2dO1I0iI.png",
      "name": "Amblin Entertainment",
      "origin_country": "US"
    },
    {
      "id": 11084,
      "logo_path": null,
      "name": "Parkes/MacDonald Productions",
      "origin_country": "US"
    }
  ],
  "production_countries": [
    {
      "iso_3166_1": "US",
      "name": "United States of America"
    }
  ],
  "release_date": "2004-06-17",
  "revenue": 219417255,
  "runtime": 128,
  "spoken_languages": [
    {
      "english_name": "Bulgarian",
      "iso_639_1": "bg",
      "name": "български език"
    },
    {
      "english_name": "English",
      "iso_639_1": "en",
      "name": "English"
    },
    {
      "english_name": "French",
      "iso_639_1": "fr",
      "name": "Français"
    },
    {
      "english_name": "Russian",
      "iso_639_1": "ru",
      "name": "Pусский"
    },
    {
      "english_name": "Spanish",
      "iso_639_1": "es",
      "name": "Español"
    }
  ],
  "status": "Released",
  "tagline": "Life is waiting.",
  "title": "The Terminal",
  "video": false,
  "vote_average": 7.348,
  "vote_count": 8113
}