{
  "adult": false,
  "backdrop_path": "/3C14xx4RteMksSUwgYfI52B8Iu6.jpg",
  "belongs_to_collection": null,
  "budget": 0,
  "genres": [
    {
      "id": 53,
      "name": "Thriller"
    },
    {
      "id": 80,
      "name": "Crime"
    },
    {
      "id": 28,
      "name": "Action"
    }
  ],
  "homepage": "",
  "id": 508138,
  "imdb_id": "tt8009314",
  "origin_country": [
    "US"
  ],
  "original_language": "en",
  "original_title": "Burn",
  "overview": "Lonely, unstable gas station attendant Melinda is tired of being overshadowed by her more confident, outgoing co-worker Sheila. When the gas station is held up at gunpoint by Billy, a desperate man in need of quick cash, Melinda finds an opportunity to make a connection with the robber, regardless of who gets hurt.",
  "popularity": 8.0069,
  "poster_path": "/ifSMo5x7SDXpettRt8TWY9EOquM.jpg",
  "production_companies": [
    {
      "id": 51954,
      "logo_path": null,
      "name": "Hopscotch Pictures",
      "origin_country": "US"
    },
    {
      "id": 114814,
      "logo_path": "/rVSzG6voK307QMz4rZY3PISx7tn.png",
      "name": "Film Mode Entertainment",
      "origin_country": "US"
    },
    {
      "id": 119056,
      "logo_path": "/vbhwOf0TQ4z12GIytYGWmhPJAOz.png",
      "name": "Particular Crowd",
      "origin_country": "US"
    },
    {
      "id": 75355,
      "logo_path": "/avj80RsunqwDbOS6oLp4plRE5UQ.png",
      "name": "Yale Productions",
      "origin_country": "US"
    },
    {
      "id": 124975,
      "logo_path": null,
      "name": "Inwood Road Films",
      "origin_country": "US"
    },
    {
      "id": 170998,
      "logo_path": null,
      "name": "Automatic Entertainment",
      "origin_country": "US"
    }
  ],
  "production_countries": [
    {
      "iso_3166_1": "US",
      "name": "United States of America"
    }
  ],
  "release_date": "2019-08-23",
  "revenue": 25373,
  "runtime": 89,
  "spoken_languages": [
    {
      "english_name": "English",
      "iso_639_1": "en",
      "name": "English"
    }
  ],
  "status": "Released",
  "tagline": "Hell of a night",
  "title": "Burn",
  "video": false,
  "vote_average": 5.987,
  "vote_count": 306
}