{
  "adult": false,
  "backdrop_path": "/eCnT1kEg8uAOyoQLhxoIbqfS0xQ.jpg",
  "belongs_to_collection": null,
  "budget": 0,
  "genres": [
    {
      "id": 28,
      "name": "Action"
    },
    {
      "id": 53,
      "name": "Thriller"
    }
  ],
  "homepage": "",
  "id": 4909,
  "imdb_id": "tt0069947",
  "origin_country": [
    "US",
    "GB"
  ],
  "original_language": "en",
  "original_title": "The Day of the Jackal",
  "overview": "An international assassin known as ‘The Jackal’ is employed by disgruntled French generals to kill President Charles de Gaulle, with a dedicated gendarme on the assassin’s trail.",
  "popularity": 7.9691,
  "poster_path": "/vThgcb3JOj99yETg8WChuci4LV2.jpg",
  "production_companies": [
    {
      "id": 1408,
      "logo_path": null,
      "name": "Universal Productions France",
      "origin_country": "FR"
    },
    {
      "id": 1807,
      "logo_path": null,
      "name": "Warwick Film Productions",
      "origin_country": "GB"
    },
    {
      "id": 3968,
      "logo_path": null,
      "name": "John Woolf Productions",
      "origin_country": "GB"
    }
  ],
  "production_countries": [
    {
      "iso_3166_1": "FR",
      "name": "France"
    },
    {
      "iso_3166_1": "GB",
      "name": "United Kingdom"
    }
  ],
  "release_date": "1973-05-16",
  "revenue": 16056255,
  "runtime": 143,
  "spoken_languages": [
    {
      "english_name": "French",
      "iso_639_1": "fr",
      "name": "Français"
    },
    {
      "english_name": "Italian",
      "iso_639_1": "it",
      "name": "Italiano"
    },
    {
      "english_name": "English",
      "iso_639_1": "en",
      "name": "English"
    }
  ],
  "status": "Released",
  "tagline": "Nameless, faceless... relentlessly moving towards the date with death that would rock the world.",
  "title": "The Day of the Jackal",
  "video": false,
  "vote_average": 7.528,
  "vote_count": 603
}