{
  "adult": false,
  "backdrop_path": "/kuYZz7aRnZvsyYyXwjuMCy0dPj4.jpg",
  "belongs_to_collection": null,
  "budget": 0,
  "genres": [
    {
      "id": 28,
      "name": "Action"
    },
    {
      "id": 35,
      "name": "Comedy"
    }
  ],
  "homepage": "https://theavenue.film/movies/old-guy",
  "id": 1077782,
  "imdb_id": "tt26442053",
  "origin_country": [
    "US",
    "GB"
  ],
  "original_language": "en",
  "original_title": "Old Guy",
  "overview": "Stuck at a dead end but vying for the love of spunky club manager Anata, aging contract killer Danny Dolinski is thrilled when The Company pulls him back in the field, but only to train Gen Z newcomer Wihlborg, a prodigy assassin with an attitude.",
  "popularity": 18.1077,
  "poster_path": "/ulVVfNY8bmy1RbHfY4zi3fOwGzh.jpg",
  "production_companies": [
    {
      "id": 104678,
      "logo_path": "/kdFFpWu5r2ziY9xXPrqhiWS9id8.png",
      "name": "23ten",
      "origin_country": "GB"
    },
    {
      "id": 164800,
      "logo_path": "/qZHPu9QptBtyCRtHhigklmPWvaQ.png",
      "name": "Source Management + Production",
      "origin_country": "US"
    },
    {
      "id": 125584,
      "logo_path": "/56Lrmj9izLx7SEa0uPp0fVvssea.png",
      "name": "Aperture Media Partners",
      "origin_country": "US"
    },
    {
      "id": 105876,
      "logo_path": null,
      "name": "Pfaff & Pfaff Productions",
      "origin_country": "US"
    },
    {
      "id": 96310,
      "logo_path": "/tBxSNuzARadiaBpIJ3qmdPG5BCz.png",
      "name": "LB Entertainment",
      "origin_country": "US"
    },
    {
      "id": 94196,
      "logo_path": "/1zcO8EP4GynujCDmqatPdye8tWZ.png",
      "name": "Wee Buns Films",
      "origin_country": "GB"
    },
    {
      "id": 11667,
      "logo_path": "/dhBJdstAolGmqRfbQfElhsU1cTo.png",
      "name": "Northern Ireland Screen",
      "origin_country": "GB"
    },
    {
      "id": 76991,
      "logo_path": "/pQjdvbv4y9yuIDSHDEHc9ijJKaS.png",
      "name": "Highland Film Group",
      "origin_country": "US"
    },
    {
      "id": 155595,
      "logo_path": null,
      "name": "Yellow Moon",
      "origin_country": "GB"
    },
    {
      "id": 1786,
      "logo_path": "/dVSnNBwhb0WW5zGis3HjI6Q66Gp.png",
      "name": "Dark Castle Entertainment",
      "origin_country": "US"
    }
  ],
  "production_countries": [
    {
      "iso_3166_1": "GB",
      "name": "United Kingdom"
    },
    {
      "iso_3166_1": "US",
      "name": "United States of America"
    }
  ],
  "release_date": "2024-12-13",
  "revenue": 0,
  "runtime": 93,
  "spoken_languages": [
    {
      "english_name": "English",
      "iso_639_1": "en",
      "name": "English"
    }
  ],
  "status": "Released",
  "tagline": "Competition is always a killer.",
  "title": "Old Guy",
  "video": false,
  "vote_average": 5.702,
  "vote_count": 104
}